{
	"songs": [
		[
			"Philly Nice",
			"senpai-pixel",
			[
				255,
				233,
				0
			]
		],
		[
			"Blammed",
			"senpai-pixel",
			[
				255,
				233,
				0
			]
		],
		[
			"Satin Panties",
			"mom",
			[
				255,
				255,
				255
			]
		],
		[
			"High",
			"tankman",
			[
				40,
				40,
				40
			]
		],
		[
			"Milf",
			"tankman",
			[
				40,
				40,
				40
			]
		]
	],
	"weekCharacters": [
		"dad",
		"bf",
		"gf"
	],
	"weekBackground": "stage",
	"weekBefore": "tutorial",
	"storyName": "Airship Atrocities",
	"weekName": "Custom Week",
	"freeplayColor": [
		146,
		113,
		253
	],
	"startUnlocked": true,
	"hideStoryMode": false,
	"hideFreeplay": false,
	"difficulties": "Hard"
}